{"villages":[{"level":"5","name":"一街村委会","code":"130205100201"},{"level":"5","name":"二街村委会","code":"130205100202"},{"level":"5","name":"三街村委会","code":"130205100203"},{"level":"5","name":"四街村委会","code":"130205100204"},{"level":"5","name":"五街村委会","code":"130205100205"},{"level":"5","name":"六街村委会","code":"130205100206"},{"level":"5","name":"七街村委会","code":"130205100207"},{"level":"5","name":"赵庄村委会","code":"130205100208"},{"level":"5","name":"丰山村委会","code":"130205100209"},{"level":"5","name":"马路村委会","code":"130205100210"},{"level":"5","name":"马家沟村委会","code":"130205100211"},{"level":"5","name":"前屈村委会","code":"130205100212"},{"level":"5","name":"中屈村委会","code":"130205100213"},{"level":"5","name":"小屈村委会","code":"130205100214"},{"level":"5","name":"前陡河村委会","code":"130205100215"},{"level":"5","name":"后陡河村委会","code":"130205100216"},{"level":"5","name":"后屯村委会","code":"130205100217"},{"level":"5","name":"上村村委会","code":"130205100218"},{"level":"5","name":"耿家营村委会","code":"130205100219"},{"level":"5","name":"半壁店村委会","code":"130205100220"},{"level":"5","name":"国各庄村委会","code":"130205100221"},{"level":"5","name":"欢套村委会","code":"130205100222"},{"level":"5","name":"石泉庄村委会","code":"130205100223"},{"level":"5","name":"大岔道村委会","code":"130205100224"},{"level":"5","name":"岔道村委会","code":"130205100225"},{"level":"5","name":"陈庄村委会","code":"130205100226"},{"level":"5","name":"西帅甲村委会","code":"130205100227"},{"level":"5","name":"东帅甲村委会","code":"130205100228"},{"level":"5","name":"马大寨村委会","code":"130205100229"},{"level":"5","name":"石家庄村委会","code":"130205100230"},{"level":"5","name":"聂各庄村委会","code":"130205100231"},{"level":"5","name":"东八里村委会","code":"130205100232"},{"level":"5","name":"中八里村委会","code":"130205100233"},{"level":"5","name":"西八里村委会","code":"130205100234"}]}