{"villages":[{"level":"5","name":"套里庄村委会","code":"130725206201"},{"level":"5","name":"三里庄村委会","code":"130725206202"},{"level":"5","name":"西城窑村委会","code":"130725206203"},{"level":"5","name":"洗马林窑村委会","code":"130725206204"},{"level":"5","name":"小坝子村委会","code":"130725206205"},{"level":"5","name":"缸房厂村委会","code":"130725206206"},{"level":"5","name":"元卜洞村委会","code":"130725206207"},{"level":"5","name":"小井洼村委会","code":"130725206208"},{"level":"5","name":"小山井沟村委会","code":"130725206209"},{"level":"5","name":"小西沟村委会","code":"130725206210"}]}