{"villages":[{"level":"5","name":"石灰窑村委会","code":"130821209201"},{"level":"5","name":"六道河村委会","code":"130821209202"},{"level":"5","name":"河西村委会","code":"130821209203"},{"level":"5","name":"毛兰沟村委会","code":"130821209204"},{"level":"5","name":"药王庙村委会","code":"130821209205"},{"level":"5","name":"野猪河村委会","code":"130821209206"},{"level":"5","name":"南三道河子村委会","code":"130821209207"},{"level":"5","name":"小范杖子村委会","code":"130821209208"},{"level":"5","name":"黄家沟村委会","code":"130821209209"},{"level":"5","name":"小郭杖子村委会","code":"130821209210"},{"level":"5","name":"富裕村委会","code":"130821209211"},{"level":"5","name":"梁杖子村委会","code":"130821209212"},{"level":"5","name":"大范杖子村委会","code":"130821209213"},{"level":"5","name":"永兴村委会","code":"130821209214"},{"level":"5","name":"振兴村委会","code":"130821209215"},{"level":"5","name":"柳树营村委会","code":"130821209216"},{"level":"5","name":"沙金沟村委会","code":"130821209217"}]}