{"villages":[{"level":"5","name":"三沟村委会","code":"130821104201"},{"level":"5","name":"新房子村委会","code":"130821104202"},{"level":"5","name":"致富村委会","code":"130821104203"},{"level":"5","name":"兴旺村委会","code":"130821104204"},{"level":"5","name":"太平村委会","code":"130821104205"},{"level":"5","name":"山神庙村委会","code":"130821104206"},{"level":"5","name":"甲皮山村委会","code":"130821104207"},{"level":"5","name":"三道河子村委会","code":"130821104208"},{"level":"5","name":"上二道河子村委会","code":"130821104209"},{"level":"5","name":"下二道河子村委会","code":"130821104210"},{"level":"5","name":"东庄村委会","code":"130821104211"},{"level":"5","name":"北孤山村委会","code":"130821104212"},{"level":"5","name":"苏家营村委会","code":"130821104213"},{"level":"5","name":"北杖子村委会","code":"130821104214"},{"level":"5","name":"二沟村委会","code":"130821104215"},{"level":"5","name":"肖杖子村委会","code":"130821104216"},{"level":"5","name":"梁前村委会","code":"130821104217"},{"level":"5","name":"平台村委会","code":"130821104218"},{"level":"5","name":"应杖子村委会","code":"130821104219"},{"level":"5","name":"小南沟村委会","code":"130821104220"},{"level":"5","name":"大老爷庙村委会","code":"130821104221"}]}