{"villages":[{"level":"5","name":"金井村委会","code":"140802201200"},{"level":"5","name":"大井村委会","code":"140802201201"},{"level":"5","name":"侯村村委会","code":"140802201202"},{"level":"5","name":"赤社村委会","code":"140802201203"},{"level":"5","name":"南扶村委会","code":"140802201204"},{"level":"5","name":"贵家营村委会","code":"140802201205"},{"level":"5","name":"东曲樊村委会","code":"140802201206"},{"level":"5","name":"西曲樊村委会","code":"140802201207"},{"level":"5","name":"谢家营村委会","code":"140802201208"},{"level":"5","name":"卫唐村委会","code":"140802201209"},{"level":"5","name":"卫褚村委会","code":"140802201210"},{"level":"5","name":"洗马村委会","code":"140802201211"},{"level":"5","name":"西王村委会","code":"140802201212"}]}