{"villages":[{"level":"5","name":"西府社区居民委员会","code":"141182001001"},{"level":"5","name":"鼓楼南社区居民委员会","code":"141182001002"},{"level":"5","name":"小南关社区居民委员会","code":"141182001003"},{"level":"5","name":"海洪社区居民委员会","code":"141182001004"},{"level":"5","name":"南薰楼社区居民委员会","code":"141182001005"},{"level":"5","name":"建昌村委会","code":"141182001200"},{"level":"5","name":"昌宁宫村委会","code":"141182001201"},{"level":"5","name":"东南村委会","code":"141182001202"},{"level":"5","name":"东关村委会","code":"141182001203"},{"level":"5","name":"南关村委会","code":"141182001204"},{"level":"5","name":"洪南社村委会","code":"141182001205"}]}