{"cities":[{"level":"2","name":"呼和浩特市","code":"150100000000"},{"level":"2","name":"包头市","code":"150200000000"},{"level":"2","name":"乌海市","code":"150300000000"},{"level":"2","name":"赤峰市","code":"150400000000"},{"level":"2","name":"通辽市","code":"150500000000"},{"level":"2","name":"鄂尔多斯市","code":"150600000000"},{"level":"2","name":"呼伦贝尔市","code":"150700000000"},{"level":"2","name":"巴彦淖尔市","code":"150800000000"},{"level":"2","name":"乌兰察布市","code":"150900000000"},{"level":"2","name":"兴安盟","code":"152200000000"},{"level":"2","name":"锡林郭勒盟","code":"152500000000"},{"level":"2","name":"阿拉善盟","code":"152900000000"}]}