{"villages":[{"level":"5","name":"北淖村委会","code":"150121102200"},{"level":"5","name":"南淖村委会","code":"150121102201"},{"level":"5","name":"五里桥村委会","code":"150121102202"},{"level":"5","name":"喇嘛营村委会","code":"150121102203"},{"level":"5","name":"保同河村委会","code":"150121102204"},{"level":"5","name":"善岱村委会","code":"150121102205"},{"level":"5","name":"召上村委会","code":"150121102206"},{"level":"5","name":"里素村委会","code":"150121102207"},{"level":"5","name":"安民村委会","code":"150121102208"},{"level":"5","name":"南兵州亥村委会","code":"150121102209"},{"level":"5","name":"什拉村委会","code":"150121102210"},{"level":"5","name":"后善岱村委会","code":"150121102211"},{"level":"5","name":"沙梁村委会","code":"150121102212"},{"level":"5","name":"朝号村委会","code":"150121102213"},{"level":"5","name":"南董家营村委会","code":"150121102214"},{"level":"5","name":"大野场村委会","code":"150121102215"},{"level":"5","name":"大岱村委会","code":"150121102216"},{"level":"5","name":"公布村委会","code":"150121102217"},{"level":"5","name":"独立坝村委会","code":"150121102218"},{"level":"5","name":"陕西营村委会","code":"150121102219"},{"level":"5","name":"依肯板村委会","code":"150121102220"},{"level":"5","name":"巩家圪旦村委会","code":"150121102221"},{"level":"5","name":"小沙金图村委会","code":"150121102222"},{"level":"5","name":"大沙金图村委会","code":"150121102223"},{"level":"5","name":"十二犋牛村委会","code":"150121102224"},{"level":"5","name":"周家明村委会","code":"150121102225"},{"level":"5","name":"大三和城村委会","code":"150121102226"},{"level":"5","name":"小三和城村委会","code":"150121102227"}]}