{"villages":[{"level":"5","name":"永旺村委会","code":"150821103200"},{"level":"5","name":"光胜村委会","code":"150821103201"},{"level":"5","name":"民利村委会","code":"150821103202"},{"level":"5","name":"合少村委会","code":"150821103203"},{"level":"5","name":"永生村委会","code":"150821103204"},{"level":"5","name":"旭日村委会","code":"150821103205"},{"level":"5","name":"永胜村委会","code":"150821103206"},{"level":"5","name":"永联村委会","code":"150821103207"},{"level":"5","name":"团结村委会","code":"150821103208"},{"level":"5","name":"永丰村委会","code":"150821103209"},{"level":"5","name":"创业村委会","code":"150821103210"},{"level":"5","name":"光明村委会","code":"150821103211"},{"level":"5","name":"光联村委会","code":"150821103212"},{"level":"5","name":"联胜村委会","code":"150821103213"},{"level":"5","name":"丰联村委会","code":"150821103214"}]}