{"towns":[{"level":"4","name":"叶柏寿街道","code":"211322001000"},{"level":"4","name":"红山街道","code":"211322002000"},{"level":"4","name":"铁南街道","code":"211322003000"},{"level":"4","name":"万寿街道","code":"211322004000"},{"level":"4","name":"富山街道","code":"211322005000"},{"level":"4","name":"朱碌科镇","code":"211322101000"},{"level":"4","name":"建平镇","code":"211322102000"},{"level":"4","name":"黑水镇","code":"211322103000"},{"level":"4","name":"喀喇沁镇","code":"211322104000"},{"level":"4","name":"北二十家子镇","code":"211322105000"},{"level":"4","name":"沙海镇","code":"211322106000"},{"level":"4","name":"哈拉道口镇","code":"211322108000"},{"level":"4","name":"榆树林子镇","code":"211322109000"},{"level":"4","name":"老官地镇","code":"211322110000"},{"level":"4","name":"深井镇","code":"211322111000"},{"level":"4","name":"奎德素镇","code":"211322112000"},{"level":"4","name":"小塘镇","code":"211322113000"},{"level":"4","name":"马场镇","code":"211322114000"},{"level":"4","name":"昌隆镇","code":"211322115000"},{"level":"4","name":"张家营子镇","code":"211322117000"},{"level":"4","name":"青峰山镇","code":"211322118000"},{"level":"4","name":"青松岭乡","code":"211322205000"},{"level":"4","name":"杨树岭乡","code":"211322206000"},{"level":"4","name":"罗福沟乡","code":"211322209000"},{"level":"4","name":"烧锅营子乡","code":"211322211000"},{"level":"4","name":"太平庄乡","code":"211322213000"},{"level":"4","name":"白山乡","code":"211322214000"},{"level":"4","name":"三家蒙古族乡","code":"211322218000"},{"level":"4","name":"义成功乡","code":"211322220000"},{"level":"4","name":"八家国营农场","code":"211322400000"},{"level":"4","name":"热水国营畜牧农场","code":"211322401000"}]}