{"villages":[{"level":"5","name":"胜利街居委会","code":"220523101001"},{"level":"5","name":"解放街居委会","code":"220523101002"},{"level":"5","name":"城关村委会","code":"220523101200"},{"level":"5","name":"东关村委会","code":"220523101201"},{"level":"5","name":"西关村委会","code":"220523101202"},{"level":"5","name":"集贤村委会","code":"220523101203"},{"level":"5","name":"长安村委会","code":"220523101204"},{"level":"5","name":"高升村委会","code":"220523101205"},{"level":"5","name":"松树村委会","code":"220523101206"},{"level":"5","name":"七合村委会","code":"220523101207"},{"level":"5","name":"永兴村委会","code":"220523101208"},{"level":"5","name":"复兴村委会","code":"220523101209"},{"level":"5","name":"大阳村委会","code":"220523101210"},{"level":"5","name":"东升村委会","code":"220523101211"}]}