{"villages":[{"level":"5","name":"富民居委会","code":"220724106001"},{"level":"5","name":"三井子村委会","code":"220724106200"},{"level":"5","name":"德安村委会","code":"220724106201"},{"level":"5","name":"太安村委会","code":"220724106202"},{"level":"5","name":"永久村委会","code":"220724106203"},{"level":"5","name":"二井子村委会","code":"220724106204"},{"level":"5","name":"新井村委会","code":"220724106205"},{"level":"5","name":"头井子村委会","code":"220724106206"},{"level":"5","name":"五井子村委会","code":"220724106207"},{"level":"5","name":"六井子村委会","code":"220724106208"},{"level":"5","name":"七井子村委会","code":"220724106209"},{"level":"5","name":"西围子村委会","code":"220724106210"},{"level":"5","name":"万宝村委会","code":"220724106211"},{"level":"5","name":"纪家村委会","code":"220724106212"},{"level":"5","name":"黄家村委会","code":"220724106213"},{"level":"5","name":"八百村委会","code":"220724106214"},{"level":"5","name":"八井子村委会","code":"220724106215"},{"level":"5","name":"二龙山村委会","code":"220724106216"},{"level":"5","name":"永和村委会","code":"220724106217"},{"level":"5","name":"万泉村委会","code":"220724106218"},{"level":"5","name":"万新村委会","code":"220724106219"},{"level":"5","name":"万众村委会","code":"220724106220"},{"level":"5","name":"天启村委会","code":"220724106221"},{"level":"5","name":"庆丰村委会","code":"220724106222"},{"level":"5","name":"龙盛村委会","code":"220724106223"},{"level":"5","name":"龙福村委会","code":"220724106224"},{"level":"5","name":"七里村委会","code":"220724106225"},{"level":"5","name":"四方村委会","code":"220724106226"},{"level":"5","name":"腰岗子村委会","code":"220724106227"},{"level":"5","name":"牧场村委会","code":"220724106228"}]}