{"villages":[{"level":"5","name":"燕江路社区居委会","code":"320107005001"},{"level":"5","name":"方家营社区居委会","code":"320107005002"},{"level":"5","name":"幕府西路社区居委会","code":"320107005003"},{"level":"5","name":"金陵新四村社区居委会","code":"320107005004"},{"level":"5","name":"宝塔桥东街社区居委会","code":"320107005005"},{"level":"5","name":"金陵新六村社区居委会","code":"320107005006"},{"level":"5","name":"象山社区居委会","code":"320107005007"},{"level":"5","name":"金陵二村社区居委会","code":"320107005008"},{"level":"5","name":"燕江园社区居委会","code":"320107005009"},{"level":"5","name":"水关桥社区居委会","code":"320107005010"},{"level":"5","name":"恒盛嘉园社区居委会","code":"320107005011"}]}