{"villages":[{"level":"5","name":"科技园社区居委会","code":"320105002001"},{"level":"5","name":"中城社区居委会","code":"320105002002"},{"level":"5","name":"双和园社区居委会","code":"320105002003"},{"level":"5","name":"中奥社区居委会","code":"320105002004"},{"level":"5","name":"中胜社区居委会","code":"320105002005"},{"level":"5","name":"莲花北苑社区居委会","code":"320105002006"},{"level":"5","name":"沙洲村委会","code":"320105002200"},{"level":"5","name":"中和村委会","code":"320105002201"},{"level":"5","name":"莲花村委会","code":"320105002202"},{"level":"5","name":"双和村委会","code":"320105002203"},{"level":"5","name":"青石村委会","code":"320105002204"}]}