{"villages":[{"level":"5","name":"民主社区居民委员会","code":"320282103001"},{"level":"5","name":"翔圩村村民委员会","code":"320282103200"},{"level":"5","name":"佘圩村村民委员会","code":"320282103201"},{"level":"5","name":"南星村村民委员会","code":"320282103202"},{"level":"5","name":"美栖村村民委员会","code":"320282103203"},{"level":"5","name":"潘东村村民委员会","code":"320282103204"},{"level":"5","name":"潘家坝村村民委员会","code":"320282103205"},{"level":"5","name":"丰台村村民委员会","code":"320282103206"},{"level":"5","name":"并利村村民委员会","code":"320282103207"},{"level":"5","name":"长福村村民委员会","code":"320282103208"},{"level":"5","name":"宜丰村村民委员会","code":"320282103209"},{"level":"5","name":"东岳村村民委员会","code":"320282103210"},{"level":"5","name":"烟山村村民委员会","code":"320282103212"},{"level":"5","name":"鲸塘村村民委员会","code":"320282103213"},{"level":"5","name":"胥藏村村民委员会","code":"320282103216"},{"level":"5","name":"盛家村村民委员会","code":"320282103217"},{"level":"5","name":"堰头村村民委员会","code":"320282103219"},{"level":"5","name":"汤泉村村民委员会","code":"320282103220"},{"level":"5","name":"西墟村村民委员会","code":"320282103222"},{"level":"5","name":"联星村村民委员会","code":"320282103223"},{"level":"5","name":"奖墅村村民委员会","code":"320282103225"},{"level":"5","name":"芳庄村村民委员会","code":"320282103226"},{"level":"5","name":"五牧村村民委员会","code":"320282103228"},{"level":"5","name":"邮堂村村民委员会","code":"320282103229"}]}