{"villages":[{"level":"5","name":"西塘社区居委会","code":"320584104001"},{"level":"5","name":"河西社区居委会","code":"320584104002"},{"level":"5","name":"南大社区居委会","code":"320584104003"},{"level":"5","name":"新建社区居委会","code":"320584104004"},{"level":"5","name":"南新社区居委会","code":"320584104005"},{"level":"5","name":"新诚社区居委会","code":"320584104006"},{"level":"5","name":"梅堰社区居委会","code":"320584104007"},{"level":"5","name":"群星村委会","code":"320584104200"},{"level":"5","name":"金联村委会","code":"320584104201"},{"level":"5","name":"联丰村委会","code":"320584104202"},{"level":"5","name":"胜墩村委会","code":"320584104203"},{"level":"5","name":"平西村委会","code":"320584104204"},{"level":"5","name":"上横村委会","code":"320584104205"},{"level":"5","name":"溪港村委会","code":"320584104206"},{"level":"5","name":"南杨村委会","code":"320584104207"},{"level":"5","name":"顾扇村委会","code":"320584104208"},{"level":"5","name":"莺湖村委会","code":"320584104209"},{"level":"5","name":"端市村委会","code":"320584104210"},{"level":"5","name":"中鲈村委会","code":"320584104211"},{"level":"5","name":"万心村委会","code":"320584104212"},{"level":"5","name":"龙南村委会","code":"320584104213"},{"level":"5","name":"庙头村委会","code":"320584104214"},{"level":"5","name":"联合村委会","code":"320584104215"},{"level":"5","name":"双浜村委会","code":"320584104216"},{"level":"5","name":"新南村委会","code":"320584104217"},{"level":"5","name":"平安村委会","code":"320584104218"},{"level":"5","name":"秋泽村委会","code":"320584104219"},{"level":"5","name":"三官桥村委会","code":"320584104220"}]}