{"villages":[{"level":"5","name":"中桥社区居委会","code":"320602009001"},{"level":"5","name":"太平社区居委会","code":"320602009002"},{"level":"5","name":"山港桥社区居委会","code":"320602009003"},{"level":"5","name":"学堂桥社区居委会","code":"320602009004"},{"level":"5","name":"十八湾社区居委会","code":"320602009005"},{"level":"5","name":"中沙社区居委会","code":"320602009006"},{"level":"5","name":"盘香沟社区居委会","code":"320602009007"},{"level":"5","name":"世伦桥社区居委会","code":"320602009008"},{"level":"5","name":"海洪社区居委会","code":"320602009009"},{"level":"5","name":"朝东埭社区居委会","code":"320602009010"},{"level":"5","name":"埭伍桥社区居委会","code":"320602009011"},{"level":"5","name":"国胜社区居委会","code":"320602009012"},{"level":"5","name":"三桥社区居委会","code":"320602009013"},{"level":"5","name":"二桥社区居委会","code":"320602009014"},{"level":"5","name":"新胜社区居委会","code":"320602009015"},{"level":"5","name":"青龙桥社区居委会","code":"320602009016"}]}