{"villages":[{"level":"5","name":"新河路社区居委会","code":"321181100001"},{"level":"5","name":"光明路社区居委会","code":"321181100002"},{"level":"5","name":"东风路社区居委会","code":"321181100003"},{"level":"5","name":"杏虎村委会","code":"321181100200"},{"level":"5","name":"河阳村委会","code":"321181100201"},{"level":"5","name":"三桥村委会","code":"321181100202"},{"level":"5","name":"吴塘村委会","code":"321181100203"},{"level":"5","name":"谭巷村委会","code":"321181100204"},{"level":"5","name":"固村村委会","code":"321181100205"},{"level":"5","name":"杏村村委会","code":"321181100206"},{"level":"5","name":"东风村委会","code":"321181100207"},{"level":"5","name":"薛甲村委会","code":"321181100208"},{"level":"5","name":"张寺村委会","code":"321181100209"},{"level":"5","name":"屯甸村委会","code":"321181100210"},{"level":"5","name":"丁庄村委会","code":"321181100211"},{"level":"5","name":"培棠村委会","code":"321181100212"}]}