{"villages":[{"level":"5","name":"关庙居委会","code":"321311111001"},{"level":"5","name":"崇河居委会","code":"321311111002"},{"level":"5","name":"乔口居委会","code":"321311111003"},{"level":"5","name":"二元村委会","code":"321311111200"},{"level":"5","name":"董圩村委会","code":"321311111201"},{"level":"5","name":"永平村委会","code":"321311111202"},{"level":"5","name":"仁和村委会","code":"321311111203"},{"level":"5","name":"泰山村委会","code":"321311111204"},{"level":"5","name":"董墩村委会","code":"321311111205"},{"level":"5","name":"长兴村委会","code":"321311111206"},{"level":"5","name":"水汉村委会","code":"321311111207"},{"level":"5","name":"卓庄村委会","code":"321311111208"},{"level":"5","name":"林河村委会","code":"321311111209"},{"level":"5","name":"陆相村委会","code":"321311111210"}]}