{"villages":[{"level":"5","name":"振宁社区","code":"330109110002"},{"level":"5","name":"金二社区","code":"330109110003"},{"level":"5","name":"金一社区","code":"330109110004"},{"level":"5","name":"宁安社区","code":"330109110005"},{"level":"5","name":"宁东社区","code":"330109110006"},{"level":"5","name":"宁税社区","code":"330109110007"},{"level":"5","name":"佳境社区","code":"330109110008"},{"level":"5","name":"新华村委会","code":"330109110205"},{"level":"5","name":"宁新村委会","code":"330109110206"},{"level":"5","name":"宁牧村委会","code":"330109110207"},{"level":"5","name":"新安村委会","code":"330109110208"},{"level":"5","name":"顺坝村委会","code":"330109110210"},{"level":"5","name":"新中村委会","code":"330109110211"},{"level":"5","name":"丰东村委会","code":"330109110213"},{"level":"5","name":"盈一村委会","code":"330109110214"},{"level":"5","name":"盈二村委会","code":"330109110215"},{"level":"5","name":"丰二村委会","code":"330109110216"},{"level":"5","name":"丰北村委会","code":"330109110217"},{"level":"5","name":"合丰村委会","code":"330109110218"},{"level":"5","name":"利一村委会","code":"330109110219"},{"level":"5","name":"利二村委会","code":"330109110220"},{"level":"5","name":"二桥村委会","code":"330109110221"}]}