{"villages":[{"level":"5","name":"东莹社区居委会","code":"330723107001"},{"level":"5","name":"上茭道村委会","code":"330723107200"},{"level":"5","name":"沈家村委会","code":"330723107201"},{"level":"5","name":"下茭道村委会","code":"330723107202"},{"level":"5","name":"董村村委会","code":"330723107203"},{"level":"5","name":"罗山村委会","code":"330723107204"},{"level":"5","name":"上下坑村委会","code":"330723107205"},{"level":"5","name":"南仓村委会","code":"330723107206"},{"level":"5","name":"蒋马洞村委会","code":"330723107207"},{"level":"5","name":"朱王村委会","code":"330723107208"},{"level":"5","name":"麻栗畈村委会","code":"330723107209"},{"level":"5","name":"沙溪村委会","code":"330723107210"},{"level":"5","name":"胡宅垄村委会","code":"330723107211"}]}