{"villages":[{"level":"5","name":"三里桥居委会","code":"341125100001"},{"level":"5","name":"迎宾路居委会","code":"341125100002"},{"level":"5","name":"西大街居委会","code":"341125100003"},{"level":"5","name":"北大街居委会","code":"341125100004"},{"level":"5","name":"南大街回民居委会","code":"341125100005"},{"level":"5","name":"人民路居委会","code":"341125100006"},{"level":"5","name":"长征路居委会","code":"341125100007"},{"level":"5","name":"靠城路居委会","code":"341125100008"},{"level":"5","name":"南环路居委会","code":"341125100009"},{"level":"5","name":"市场路居委会","code":"341125100010"},{"level":"5","name":"严桥路居委会","code":"341125100011"},{"level":"5","name":"幸福路居委会","code":"341125100012"},{"level":"5","name":"泉坞山居委会","code":"341125100013"},{"level":"5","name":"长青居委会","code":"341125100014"},{"level":"5","name":"城北居委会","code":"341125100015"},{"level":"5","name":"南塘居委会","code":"341125100016"},{"level":"5","name":"花园湖居委会","code":"341125100017"},{"level":"5","name":"双塘居委会","code":"341125100018"},{"level":"5","name":"定东村委会","code":"341125100202"},{"level":"5","name":"东顾村委会","code":"341125100203"},{"level":"5","name":"丰收村委会","code":"341125100204"},{"level":"5","name":"双庙村委会","code":"341125100205"},{"level":"5","name":"定西村委会","code":"341125100207"},{"level":"5","name":"城南村委会","code":"341125100208"},{"level":"5","name":"棠店村委会","code":"341125100209"},{"level":"5","name":"解放村委会","code":"341125100210"},{"level":"5","name":"岗上村委会","code":"341125100211"},{"level":"5","name":"何庄村委会","code":"341125100212"},{"level":"5","name":"程桥村委会","code":"341125100213"},{"level":"5","name":"连环村委会","code":"341125100214"},{"level":"5","name":"宫集村委会","code":"341125100215"},{"level":"5","name":"十八岗村委会","code":"341125100216"},{"level":"5","name":"岗刘村委会","code":"341125100217"},{"level":"5","name":"斋朗村委会","code":"341125100218"},{"level":"5","name":"民生村委会","code":"341125100219"},{"level":"5","name":"友谊村委会","code":"341125100220"},{"level":"5","name":"回民村委会","code":"341125100221"}]}