{"villages":[{"level":"5","name":"丹城居委会","code":"341621116001"},{"level":"5","name":"常庄村委会","code":"341621116200"},{"level":"5","name":"白果村委会","code":"341621116201"},{"level":"5","name":"相老家村委会","code":"341621116202"},{"level":"5","name":"相楼村委会","code":"341621116203"},{"level":"5","name":"徐楼村委会","code":"341621116204"},{"level":"5","name":"红旗村委会","code":"341621116205"},{"level":"5","name":"谢庙村委会","code":"341621116206"},{"level":"5","name":"齐西村委会","code":"341621116207"},{"level":"5","name":"董阁村委会","code":"341621116208"},{"level":"5","name":"齐东村委会","code":"341621116209"},{"level":"5","name":"重兴村委会","code":"341621116210"},{"level":"5","name":"重南村委会","code":"341621116211"},{"level":"5","name":"岭孜村委会","code":"341621116212"},{"level":"5","name":"陈老家村委会","code":"341621116213"},{"level":"5","name":"王阁村委会","code":"341621116214"}]}