{"towns":[{"level":"4","name":"翠江镇","code":"350424100000"},{"level":"4","name":"泉上镇","code":"350424101000"},{"level":"4","name":"湖村镇","code":"350424102000"},{"level":"4","name":"石壁镇","code":"350424103000"},{"level":"4","name":"城郊乡","code":"350424200000"},{"level":"4","name":"城南乡","code":"350424201000"},{"level":"4","name":"济村乡","code":"350424202000"},{"level":"4","name":"淮土乡","code":"350424203000"},{"level":"4","name":"方田乡","code":"350424204000"},{"level":"4","name":"安乐乡","code":"350424205000"},{"level":"4","name":"曹坊乡","code":"350424206000"},{"level":"4","name":"治平畲族乡","code":"350424207000"},{"level":"4","name":"中沙乡","code":"350424208000"},{"level":"4","name":"河龙乡","code":"350424209000"},{"level":"4","name":"水茜乡","code":"350424210000"},{"level":"4","name":"安远乡","code":"350424211000"}]}