{"villages":[{"level":"5","name":"白芒村民委员会","code":"360521104200"},{"level":"5","name":"新祉村民委员会","code":"360521104201"},{"level":"5","name":"堂下村民委员会","code":"360521104202"},{"level":"5","name":"庄边村民委员会","code":"360521104203"},{"level":"5","name":"金鸡布村民委员会","code":"360521104204"},{"level":"5","name":"行山村民委员会","code":"360521104205"},{"level":"5","name":"苑坑村民委员会","code":"360521104206"},{"level":"5","name":"龙源村民委员会","code":"360521104207"},{"level":"5","name":"田心村民委员会","code":"360521104208"},{"level":"5","name":"檀溪村民委员会","code":"360521104209"},{"level":"5","name":"木足村民委员会","code":"360521104210"},{"level":"5","name":"冶元村民委员会","code":"360521104211"},{"level":"5","name":"砻里村民委员会","code":"360521104212"},{"level":"5","name":"大岗山村民委员会","code":"360521104213"},{"level":"5","name":"双源村民委员会","code":"360521104214"},{"level":"5","name":"大铜村民委员会","code":"360521104215"},{"level":"5","name":"下田村民委员会","code":"360521104216"},{"level":"5","name":"松山村民委员会","code":"360521104217"},{"level":"5","name":"桥边村民委员会","code":"360521104218"},{"level":"5","name":"石枫村民委员会","code":"360521104219"},{"level":"5","name":"防里村民委员会","code":"360521104220"}]}