{"villages":[{"level":"5","name":"丽村居委会","code":"360981111001"},{"level":"5","name":"游坊村委会","code":"360981111200"},{"level":"5","name":"尚山村委会","code":"360981111201"},{"level":"5","name":"溪头村委会","code":"360981111202"},{"level":"5","name":"梅溪村委会","code":"360981111203"},{"level":"5","name":"龙潭村委会","code":"360981111204"},{"level":"5","name":"小巴村委会","code":"360981111205"},{"level":"5","name":"石溪村委会","code":"360981111206"},{"level":"5","name":"城前村委会","code":"360981111207"},{"level":"5","name":"漆家村委会","code":"360981111208"},{"level":"5","name":"樟溪村委会","code":"360981111209"},{"level":"5","name":"对木村委会","code":"360981111210"},{"level":"5","name":"扶山村委会","code":"360981111211"},{"level":"5","name":"挂甲村委会","code":"360981111212"},{"level":"5","name":"茅头村委会","code":"360981111213"},{"level":"5","name":"甘溪村委会","code":"360981111214"},{"level":"5","name":"龙兴村委会","code":"360981111215"},{"level":"5","name":"礼坊村委会","code":"360981111216"},{"level":"5","name":"根竹村委会","code":"360981111217"}]}