{"villages":[{"level":"5","name":"丁家河社区居民委员会","code":"370211005001"},{"level":"5","name":"焦家庄社区居民委员会","code":"370211005002"},{"level":"5","name":"井冈山路社区居民委员会","code":"370211005003"},{"level":"5","name":"武家庄社区居民委员会","code":"370211005004"},{"level":"5","name":"车家岭社区居民委员会","code":"370211005005"},{"level":"5","name":"西于家河社区居民委员会","code":"370211005006"},{"level":"5","name":"钱塘江路社区居民委员会","code":"370211005007"},{"level":"5","name":"官厅社区居民委员会","code":"370211005008"},{"level":"5","name":"濠北头社区居民委员会","code":"370211005009"},{"level":"5","name":"太行山路社区居民委员会","code":"370211005010"},{"level":"5","name":"武夷山路社区居民委员会","code":"370211005011"},{"level":"5","name":"东于家河社区居民委员会","code":"370211005012"},{"level":"5","name":"张宝湾社区居民委员会","code":"370211005013"},{"level":"5","name":"武当山路社区居民委员会","code":"370211005014"},{"level":"5","name":"新时代小区社区居民委员会","code":"370211005015"},{"level":"5","name":"紫金山小区社区居民委员会","code":"370211005016"},{"level":"5","name":"阿里山小区社区居民委员会","code":"370211005017"},{"level":"5","name":"香江路社区居民委员会","code":"370211005018"},{"level":"5","name":"江山南路社区居民委员会","code":"370211005019"},{"level":"5","name":"玉山路社区居民委员会","code":"370211005020"},{"level":"5","name":"富春江路社区居民委员会","code":"370211005021"},{"level":"5","name":"长江中路社区居民委员会","code":"370211005022"},{"level":"5","name":"北江支路社区居民委员会","code":"370211005023"},{"level":"5","name":"台子沟社区居民委员会","code":"370211005024"},{"level":"5","name":"八里庄社区居民委员会","code":"370211005025"},{"level":"5","name":"荒里社区居民委员会","code":"370211005026"},{"level":"5","name":"扒山社区居民委员会","code":"370211005027"},{"level":"5","name":"岔河社区居民委员会","code":"370211005028"},{"level":"5","name":"戴戈庄社区居民委员会","code":"370211005029"},{"level":"5","name":"薛辛庄社区居民委员会","code":"370211005030"},{"level":"5","name":"两埠岸社区居民委员会","code":"370211005031"},{"level":"5","name":"王家港社区居民委员会","code":"370211005032"},{"level":"5","name":"花科子社区居民委员会","code":"370211005033"},{"level":"5","name":"高家台社区居民委员会","code":"370211005034"},{"level":"5","name":"周家夼社区居民委员会","code":"370211005035"}]}