{"villages":[{"level":"5","name":"祝前村委会","code":"370283123200"},{"level":"5","name":"祝东村委会","code":"370283123201"},{"level":"5","name":"祝后村委会","code":"370283123202"},{"level":"5","name":"祝西村委会","code":"370283123203"},{"level":"5","name":"后寨子村委会","code":"370283123204"},{"level":"5","name":"东于家屯村委会","code":"370283123205"},{"level":"5","name":"洼子村委会","code":"370283123206"},{"level":"5","name":"孙戈庄村委会","code":"370283123207"},{"level":"5","name":"田家庄村委会","code":"370283123208"},{"level":"5","name":"武家庄村委会","code":"370283123209"},{"level":"5","name":"后杨家庄村委会","code":"370283123210"},{"level":"5","name":"清水村委会","code":"370283123211"},{"level":"5","name":"且戈庄村委会","code":"370283123212"},{"level":"5","name":"展王家村委会","code":"370283123213"},{"level":"5","name":"前河南村委会","code":"370283123214"},{"level":"5","name":"后河南村委会","code":"370283123215"},{"level":"5","name":"东连戈庄村委会","code":"370283123216"},{"level":"5","name":"西连戈庄村委会","code":"370283123217"},{"level":"5","name":"涌泉村委会","code":"370283123218"},{"level":"5","name":"小沽洄村委会","code":"370283123219"},{"level":"5","name":"沙埠村委会","code":"370283123220"},{"level":"5","name":"西孟村委会","code":"370283123221"},{"level":"5","name":"东孟村委会","code":"370283123222"},{"level":"5","name":"铁家庄村委会","code":"370283123223"},{"level":"5","name":"苏格庄村委会","code":"370283123224"},{"level":"5","name":"北黄同村委会","code":"370283123225"},{"level":"5","name":"南黄同村委会","code":"370283123226"},{"level":"5","name":"东李家庄村委会","code":"370283123227"},{"level":"5","name":"水磨涧村委会","code":"370283123228"},{"level":"5","name":"潘家屯村委会","code":"370283123229"},{"level":"5","name":"东店子村委会","code":"370283123230"},{"level":"5","name":"小埠子村委会","code":"370283123231"},{"level":"5","name":"大王头村委会","code":"370283123232"},{"level":"5","name":"张美夼村委会","code":"370283123233"},{"level":"5","name":"山头村委会","code":"370283123234"},{"level":"5","name":"北岔道口村委会","code":"370283123235"},{"level":"5","name":"路上村委会","code":"370283123236"},{"level":"5","name":"隋家村委会","code":"370283123237"},{"level":"5","name":"徐家屯村委会","code":"370283123238"},{"level":"5","name":"刘家庄村委会","code":"370283123239"},{"level":"5","name":"石楼院村委会","code":"370283123240"},{"level":"5","name":"河西纸房村委会","code":"370283123241"},{"level":"5","name":"前刘家村委会","code":"370283123242"},{"level":"5","name":"后刘家村委会","code":"370283123243"},{"level":"5","name":"北大流河村委会","code":"370283123244"},{"level":"5","name":"高家流河村委会","code":"370283123245"},{"level":"5","name":"小洪埠村委会","code":"370283123246"},{"level":"5","name":"大洪埠村委会","code":"370283123247"},{"level":"5","name":"山里程家村委会","code":"370283123248"},{"level":"5","name":"九山后村委会","code":"370283123249"},{"level":"5","name":"山里石家村委会","code":"370283123250"},{"level":"5","name":"王家流河村委会","code":"370283123251"},{"level":"5","name":"石家流河村委会","code":"370283123252"},{"level":"5","name":"崔家流河村委会","code":"370283123253"},{"level":"5","name":"赵家流河村委会","code":"370283123254"},{"level":"5","name":"吕家流河村委会","code":"370283123255"}]}