{"villages":[{"level":"5","name":"王营伍村委会","code":"371422201201"},{"level":"5","name":"付庙村委会","code":"371422201202"},{"level":"5","name":"刘秋村委会","code":"371422201203"},{"level":"5","name":"寨东村委会","code":"371422201204"},{"level":"5","name":"寨西村委会","code":"371422201205"},{"level":"5","name":"崔寨村委会","code":"371422201206"},{"level":"5","name":"庞寨村委会","code":"371422201207"},{"level":"5","name":"杨官马村委会","code":"371422201208"},{"level":"5","name":"于庄村委会","code":"371422201209"},{"level":"5","name":"周庄村委会","code":"371422201210"},{"level":"5","name":"东刘村委会","code":"371422201211"},{"level":"5","name":"前刘村委会","code":"371422201212"},{"level":"5","name":"后刘村委会","code":"371422201213"},{"level":"5","name":"西刘村委会","code":"371422201214"},{"level":"5","name":"曹茂伍村委会","code":"371422201215"},{"level":"5","name":"宋庄村委会","code":"371422201216"},{"level":"5","name":"贾庄村委会","code":"371422201217"},{"level":"5","name":"门庄村委会","code":"371422201218"},{"level":"5","name":"刘旺言村委会","code":"371422201219"},{"level":"5","name":"周巴斗村委会","code":"371422201220"},{"level":"5","name":"张庄村委会","code":"371422201221"},{"level":"5","name":"龙潭村委会","code":"371422201222"},{"level":"5","name":"赵庄村委会","code":"371422201223"},{"level":"5","name":"前宗村委会","code":"371422201224"},{"level":"5","name":"后宗村委会","code":"371422201225"},{"level":"5","name":"前寺村委会","code":"371422201226"},{"level":"5","name":"后寺村委会","code":"371422201227"},{"level":"5","name":"前商村委会","code":"371422201228"},{"level":"5","name":"商西村委会","code":"371422201229"},{"level":"5","name":"商东村委会","code":"371422201230"},{"level":"5","name":"孙华门村委会","code":"371422201231"},{"level":"5","name":"老君堂村委会","code":"371422201232"},{"level":"5","name":"河北张东村委会","code":"371422201233"},{"level":"5","name":"河北张西村委会","code":"371422201234"},{"level":"5","name":"郭营伍村委会","code":"371422201235"},{"level":"5","name":"刘营伍村委会","code":"371422201236"},{"level":"5","name":"张安村委会","code":"371422201237"}]}