{"villages":[{"level":"5","name":"柴市街居委会","code":"371581002001"},{"level":"5","name":"古楼街居委会","code":"371581002002"},{"level":"5","name":"东关街居委会","code":"371581002003"},{"level":"5","name":"国棉街居委会","code":"371581002004"},{"level":"5","name":"南门里街居委会","code":"371581002005"},{"level":"5","name":"元仓街居委会","code":"371581002006"},{"level":"5","name":"北门里街居委会","code":"371581002007"},{"level":"5","name":"西门里街居委会","code":"371581002008"},{"level":"5","name":"新开街居委会","code":"371581002009"},{"level":"5","name":"上湾街居委会","code":"371581002010"},{"level":"5","name":"古楼东街居委会","code":"371581002011"},{"level":"5","name":"东兴街居委会","code":"371581002012"},{"level":"5","name":"北关街居委会","code":"371581002013"},{"level":"5","name":"杨桥街居委会","code":"371581002014"},{"level":"5","name":"果园街居委会","code":"371581002015"},{"level":"5","name":"林园街居委会","code":"371581002016"},{"level":"5","name":"新北街居委会","code":"371581002017"},{"level":"5","name":"黑庄居委会","code":"371581002026"},{"level":"5","name":"北三里居委会","code":"371581002027"},{"level":"5","name":"新开居委会","code":"371581002028"},{"level":"5","name":"南门居委会","code":"371581002029"},{"level":"5","name":"古楼居委会","code":"371581002030"},{"level":"5","name":"林园居委会","code":"371581002031"},{"level":"5","name":"东关居委会","code":"371581002032"},{"level":"5","name":"东胡居委会","code":"371581002033"},{"level":"5","name":"西胡居委会","code":"371581002034"},{"level":"5","name":"鹁鸽李庄居委会","code":"371581002035"},{"level":"5","name":"北廖庄居委会","code":"371581002036"},{"level":"5","name":"刁庄居委会","code":"371581002037"},{"level":"5","name":"东陶居委会","code":"371581002038"},{"level":"5","name":"西陶居委会","code":"371581002039"},{"level":"5","name":"董街居委会","code":"371581002040"},{"level":"5","name":"王院居委会","code":"371581002041"},{"level":"5","name":"狄楼居委会","code":"371581002042"},{"level":"5","name":"郭庄居委会","code":"371581002043"},{"level":"5","name":"陈庄居委会","code":"371581002044"},{"level":"5","name":"西闫居委会","code":"371581002045"},{"level":"5","name":"东闫居委会","code":"371581002046"},{"level":"5","name":"花园居委会","code":"371581002047"},{"level":"5","name":"牛八里居委会","code":"371581002048"},{"level":"5","name":"北王院居委会","code":"371581002049"},{"level":"5","name":"千佛堂居委会","code":"371581002050"},{"level":"5","name":"唐庄居委会","code":"371581002051"},{"level":"5","name":"甄八里居委会","code":"371581002052"},{"level":"5","name":"杨八里居委会","code":"371581002053"},{"level":"5","name":"于庄居委会","code":"371581002054"},{"level":"5","name":"作西店居委会","code":"371581002055"},{"level":"5","name":"屈庄居委会","code":"371581002056"},{"level":"5","name":"张芳庄居委会","code":"371581002057"},{"level":"5","name":"龙庄居委会","code":"371581002058"},{"level":"5","name":"十二里屯居委会","code":"371581002059"},{"level":"5","name":"杨桥居委会","code":"371581002060"},{"level":"5","name":"沙窝屯居委会","code":"371581002061"},{"level":"5","name":"桑树园居委会","code":"371581002062"},{"level":"5","name":"蔡家胡同居委会","code":"371581002063"},{"level":"5","name":"陈坟居委会","code":"371581002064"},{"level":"5","name":"周三里居委会","code":"371581002065"},{"level":"5","name":"朱杨乔居委会","code":"371581002066"},{"level":"5","name":"韦付庄居委会","code":"371581002067"},{"level":"5","name":"小油坊居委会","code":"371581002068"}]}