{"villages":[{"level":"5","name":"邢家村委会","code":"371626113200"},{"level":"5","name":"苏桥村委会","code":"371626113201"},{"level":"5","name":"张辛村委会","code":"371626113202"},{"level":"5","name":"南宋村委会","code":"371626113203"},{"level":"5","name":"西闸村委会","code":"371626113204"},{"level":"5","name":"南成村委会","code":"371626113205"},{"level":"5","name":"解家村委会","code":"371626113206"},{"level":"5","name":"高洼村委会","code":"371626113207"},{"level":"5","name":"曹家村委会","code":"371626113208"},{"level":"5","name":"兰芝里村委会","code":"371626113209"},{"level":"5","name":"惠辛村委会","code":"371626113210"},{"level":"5","name":"大张官庄村委会","code":"371626113211"},{"level":"5","name":"东张村委会","code":"371626113212"},{"level":"5","name":"宋集村委会","code":"371626113213"},{"level":"5","name":"许道口村委会","code":"371626113214"},{"level":"5","name":"段桥村委会","code":"371626113215"},{"level":"5","name":"王家桥村委会","code":"371626113216"},{"level":"5","name":"柴家村委会","code":"371626113217"},{"level":"5","name":"二辛村委会","code":"371626113218"},{"level":"5","name":"颜集村委会","code":"371626113219"},{"level":"5","name":"牛官村委会","code":"371626113220"},{"level":"5","name":"窝村村委会","code":"371626113221"},{"level":"5","name":"大耿村委会","code":"371626113222"},{"level":"5","name":"牛家村委会","code":"371626113223"},{"level":"5","name":"于家村委会","code":"371626113224"},{"level":"5","name":"东左村委会","code":"371626113225"},{"level":"5","name":"王少唐村委会","code":"371626113226"},{"level":"5","name":"东闸村委会","code":"371626113227"},{"level":"5","name":"高家村委会","code":"371626113228"},{"level":"5","name":"里六田村委会","code":"371626113229"},{"level":"5","name":"西宋村委会","code":"371626113230"},{"level":"5","name":"菅家村委会","code":"371626113231"},{"level":"5","name":"罗圈村委会","code":"371626113232"},{"level":"5","name":"孙李辛村委会","code":"371626113233"},{"level":"5","name":"小耿村委会","code":"371626113234"},{"level":"5","name":"明集村委会","code":"371626113235"}]}