{"villages":[{"level":"5","name":"太山村村委会","code":"410724204201"},{"level":"5","name":"辛章村村委会","code":"410724204202"},{"level":"5","name":"小庄村村委会","code":"410724204203"},{"level":"5","name":"沙窝营村村委会","code":"410724204204"},{"level":"5","name":"西寺营村村委会","code":"410724204205"},{"level":"5","name":"东寺营村村委会","code":"410724204206"},{"level":"5","name":"塔洼村村委会","code":"410724204207"},{"level":"5","name":"程操村村委会","code":"410724204208"},{"level":"5","name":"郑庄村村委会","code":"410724204209"},{"level":"5","name":"程玉村村委会","code":"410724204210"},{"level":"5","name":"官庄村村委会","code":"410724204211"},{"level":"5","name":"罗旗营村村委会","code":"410724204212"},{"level":"5","name":"东古风村村委会","code":"410724204213"},{"level":"5","name":"晁庄村村委会","code":"410724204214"},{"level":"5","name":"李庄村村委会","code":"410724204215"},{"level":"5","name":"曹庄村村委会","code":"410724204216"},{"level":"5","name":"韩小营村村委会","code":"410724204217"},{"level":"5","name":"王庄村村委会","code":"410724204218"},{"level":"5","name":"孝合村村委会","code":"410724204219"},{"level":"5","name":"大张卜村村委会","code":"410724204220"},{"level":"5","name":"陈孝村村委会","code":"410724204221"},{"level":"5","name":"董庄村村委会","code":"410724204222"},{"level":"5","name":"丁村村委会","code":"410724204223"},{"level":"5","name":"马庄村村委会","code":"410724204224"}]}