{"villages":[{"level":"5","name":"勒马南街村委会","code":"411403208201"},{"level":"5","name":"勒马东街村委会","code":"411403208202"},{"level":"5","name":"勒马北街村委会","code":"411403208203"},{"level":"5","name":"袁楼村委会","code":"411403208204"},{"level":"5","name":"何太庄村委会","code":"411403208205"},{"level":"5","name":"朱家庄村委会","code":"411403208206"},{"level":"5","name":"吴其营村委会","code":"411403208207"},{"level":"5","name":"宋小桥村委会","code":"411403208208"},{"level":"5","name":"西杨庄村委会","code":"411403208209"},{"level":"5","name":"尤庄村委会","code":"411403208210"},{"level":"5","name":"赵几楼村委会","code":"411403208211"},{"level":"5","name":"朱关村委会","code":"411403208212"},{"level":"5","name":"闫庄村委会","code":"411403208213"},{"level":"5","name":"开荒村委会","code":"411403208214"},{"level":"5","name":"孔庄村委会","code":"411403208215"},{"level":"5","name":"王油坊村委会","code":"411403208216"},{"level":"5","name":"焦庄村委会","code":"411403208217"},{"level":"5","name":"李桥村委会","code":"411403208218"},{"level":"5","name":"宋瓦房村委会","code":"411403208219"},{"level":"5","name":"林堂村委会","code":"411403208220"},{"level":"5","name":"刘汗珠村委会","code":"411403208221"},{"level":"5","name":"刘二方楼村委会","code":"411403208222"},{"level":"5","name":"西曹庄村委会","code":"411403208223"},{"level":"5","name":"陈老家村委会","code":"411403208224"}]}