{"villages":[{"level":"5","name":"港洲村委会","code":"420114200201"},{"level":"5","name":"汉洪村委会","code":"420114200202"},{"level":"5","name":"渔樵村委会","code":"420114200203"},{"level":"5","name":"罗汉村委会","code":"420114200204"},{"level":"5","name":"九沟村委会","code":"420114200205"},{"level":"5","name":"挖沟村委会","code":"420114200206"},{"level":"5","name":"洪南村委会","code":"420114200207"},{"level":"5","name":"曲口村委会","code":"420114200208"},{"level":"5","name":"七壕村委会","code":"420114200209"},{"level":"5","name":"三合村委会","code":"420114200210"},{"level":"5","name":"洪河村委会","code":"420114200211"},{"level":"5","name":"杨庄村委会","code":"420114200212"},{"level":"5","name":"消泗乡社区居委会","code":"420114200400"}]}