{"villages":[{"level":"5","name":"河口街居委会","code":"420902201001"},{"level":"5","name":"卧龙街居委会","code":"420902201002"},{"level":"5","name":"卫东村委会","code":"420902201201"},{"level":"5","name":"七里村委会","code":"420902201202"},{"level":"5","name":"复兴村委会","code":"420902201203"},{"level":"5","name":"长湖村委会","code":"420902201204"},{"level":"5","name":"高潮村委会","code":"420902201205"},{"level":"5","name":"邓垸村委会","code":"420902201206"},{"level":"5","name":"大福村委会","code":"420902201207"},{"level":"5","name":"大明村委会","code":"420902201208"},{"level":"5","name":"群乐村委会","code":"420902201209"},{"level":"5","name":"长征村委会","code":"420902201210"},{"level":"5","name":"巩固村委会","code":"420902201211"},{"level":"5","name":"汪雷村委会","code":"420902201212"},{"level":"5","name":"金星村委会","code":"420902201213"},{"level":"5","name":"三合村委会","code":"420902201214"},{"level":"5","name":"西闸村委会","code":"420902201215"},{"level":"5","name":"八埠村委会","code":"420902201216"},{"level":"5","name":"环光村委会","code":"420902201217"},{"level":"5","name":"卧龙潭村委会","code":"420902201218"},{"level":"5","name":"饶屋村委会","code":"420902201219"},{"level":"5","name":"联益村委会","code":"420902201220"},{"level":"5","name":"夹沟村委会","code":"420902201221"},{"level":"5","name":"群丰村委会","code":"420902201222"},{"level":"5","name":"水砦村委会","code":"420902201223"},{"level":"5","name":"万红村委会","code":"420902201224"},{"level":"5","name":"白龙村委会","code":"420902201225"},{"level":"5","name":"杨林村委会","code":"420902201226"},{"level":"5","name":"茨林村委会","code":"420902201227"},{"level":"5","name":"周垸村委会","code":"420902201228"},{"level":"5","name":"熊家湾村委会","code":"420902201229"},{"level":"5","name":"新垸村委会","code":"420902201230"},{"level":"5","name":"联邦村委会","code":"420902201231"}]}