{"villages":[{"level":"5","name":"汊河街道居委会","code":"421083112001"},{"level":"5","name":"小港村委会","code":"421083112200"},{"level":"5","name":"双河村委会","code":"421083112201"},{"level":"5","name":"港洪村委会","code":"421083112202"},{"level":"5","name":"龙坑村委会","code":"421083112203"},{"level":"5","name":"龙甲村委会","code":"421083112204"},{"level":"5","name":"五爱村委会","code":"421083112205"},{"level":"5","name":"朝阳村委会","code":"421083112206"},{"level":"5","name":"洪城村委会","code":"421083112207"},{"level":"5","name":"万红村委会","code":"421083112208"},{"level":"5","name":"万丰村委会","code":"421083112209"},{"level":"5","name":"陈坊村委会","code":"421083112210"},{"level":"5","name":"晏坊村委会","code":"421083112211"},{"level":"5","name":"白云村委会","code":"421083112212"},{"level":"5","name":"鄢埠村委会","code":"421083112213"},{"level":"5","name":"邹万村委会","code":"421083112214"},{"level":"5","name":"太洪村委会","code":"421083112215"},{"level":"5","name":"麻田村委会","code":"421083112216"},{"level":"5","name":"红三村委会","code":"421083112217"},{"level":"5","name":"槎头村委会","code":"421083112218"},{"level":"5","name":"赛伍村委会","code":"421083112219"},{"level":"5","name":"黄台村委会","code":"421083112220"},{"level":"5","name":"白杨村委会","code":"421083112221"},{"level":"5","name":"汊河村委会","code":"421083112222"},{"level":"5","name":"农科村委会","code":"421083112223"},{"level":"5","name":"蔬菜村委会","code":"421083112224"},{"level":"5","name":"潭子村委会","code":"421083112225"},{"level":"5","name":"西池村委会","code":"421083112226"},{"level":"5","name":"十八家村委会","code":"421083112227"},{"level":"5","name":"金湾村委会","code":"421083112228"},{"level":"5","name":"石杨村委会","code":"421083112229"},{"level":"5","name":"新穴村委会","code":"421083112230"},{"level":"5","name":"五丰村委会","code":"421083112231"},{"level":"5","name":"曾台村委会","code":"421083112232"},{"level":"5","name":"水晶村委会","code":"421083112233"},{"level":"5","name":"颜台村委会","code":"421083112234"},{"level":"5","name":"沿湖村委会","code":"421083112235"},{"level":"5","name":"沙咀村委会","code":"421083112236"},{"level":"5","name":"甘寺村委会","code":"421083112237"},{"level":"5","name":"里湖渔场村委会","code":"421083112500"}]}