{"villages":[{"level":"5","name":"中山社区（居委会）","code":"421381003001"},{"level":"5","name":"解放社区（居委会）","code":"421381003002"},{"level":"5","name":"工新社区（居委会）","code":"421381003003"},{"level":"5","name":"车站社区（居委会）","code":"421381003004"},{"level":"5","name":"北湖社区（居委会）","code":"421381003005"},{"level":"5","name":"九皇社区（居委会）","code":"421381003006"},{"level":"5","name":"西河社区（居委会）","code":"421381003007"},{"level":"5","name":"强力社区（居委会）","code":"421381003008"},{"level":"5","name":"武元社区（居委会）","code":"421381003009"},{"level":"5","name":"芦兴社区（居委会）","code":"421381003010"},{"level":"5","name":"马鞍社区（居委会）","code":"421381003011"},{"level":"5","name":"土门村民委员会","code":"421381003200"},{"level":"5","name":"流沙冲村民委员会","code":"421381003201"},{"level":"5","name":"铁板桥村民委员会","code":"421381003202"},{"level":"5","name":"南站村民委员会","code":"421381003203"},{"level":"5","name":"南山村民委员会","code":"421381003204"},{"level":"5","name":"驼子村民委员会","code":"421381003205"},{"level":"5","name":"陡坡村民委员会","code":"421381003206"},{"level":"5","name":"竹林村民委员会","code":"421381003207"},{"level":"5","name":"松林村民委员会","code":"421381003208"},{"level":"5","name":"双岗村民委员会","code":"421381003209"}]}