{"villages":[{"level":"5","name":"莫井村村委会","code":"430424200200"},{"level":"5","name":"碰塘村村委会","code":"430424200201"},{"level":"5","name":"江山村村委会","code":"430424200202"},{"level":"5","name":"三口井村村委会","code":"430424200203"},{"level":"5","name":"建新村村委会","code":"430424200204"},{"level":"5","name":"鹅形村村委会","code":"430424200205"},{"level":"5","name":"三垅村村委会","code":"430424200206"},{"level":"5","name":"井冲村村委会","code":"430424200207"},{"level":"5","name":"四冲村村委会","code":"430424200208"},{"level":"5","name":"莫园村村委会","code":"430424200209"},{"level":"5","name":"新开田村村委会","code":"430424200210"},{"level":"5","name":"白沙村村委会","code":"430424200211"},{"level":"5","name":"何家园村村委会","code":"430424200212"}]}