{"villages":[{"level":"5","name":"花园湾社区居委会","code":"430723214001"},{"level":"5","name":"羊煤居委会","code":"430723214002"},{"level":"5","name":"新桥村委会","code":"430723214201"},{"level":"5","name":"大公村委会","code":"430723214202"},{"level":"5","name":"羊耳山村委会","code":"430723214206"},{"level":"5","name":"丫角村委会","code":"430723214207"},{"level":"5","name":"芦桥村委会","code":"430723214209"},{"level":"5","name":"水氽洞村委会","code":"430723214211"},{"level":"5","name":"老木村委会","code":"430723214212"},{"level":"5","name":"柏樟村委会","code":"430723214213"},{"level":"5","name":"古城岗村委会","code":"430723214214"},{"level":"5","name":"沿溪村委会","code":"430723214215"},{"level":"5","name":"石庄村委会","code":"430723214218"}]}