{"villages":[{"level":"5","name":"车田村村委会","code":"431021201200"},{"level":"5","name":"烟村村委会","code":"431021201201"},{"level":"5","name":"榜山村村委会","code":"431021201202"},{"level":"5","name":"长乐村村委会","code":"431021201203"},{"level":"5","name":"清和村村委会","code":"431021201204"},{"level":"5","name":"溪口村村委会","code":"431021201205"},{"level":"5","name":"龙渡村村委会","code":"431021201206"},{"level":"5","name":"起?村村委会","code":"431021201207"},{"level":"5","name":"太竹村村委会","code":"431021201208"},{"level":"5","name":"当家村村委会","code":"431021201209"},{"level":"5","name":"芙蓉村村委会","code":"431021201210"},{"level":"5","name":"峰源村村委会","code":"431021201211"}]}