{"villages":[{"level":"5","name":"东路居委会","code":"431127102001"},{"level":"5","name":"西路居委会","code":"431127102002"},{"level":"5","name":"龙江村委会","code":"431127102200"},{"level":"5","name":"毛俊村委会","code":"431127102201"},{"level":"5","name":"沙溪村委会","code":"431127102202"},{"level":"5","name":"井头村委会","code":"431127102203"},{"level":"5","name":"栗江村委会","code":"431127102204"},{"level":"5","name":"洋田村委会","code":"431127102205"},{"level":"5","name":"西岭头村委会","code":"431127102206"},{"level":"5","name":"寺湾村委会","code":"431127102207"},{"level":"5","name":"朱家村委会","code":"431127102208"},{"level":"5","name":"毛塘村委会","code":"431127102209"},{"level":"5","name":"秧田村委会","code":"431127102210"},{"level":"5","name":"鹊峰村委会","code":"431127102211"},{"level":"5","name":"漕沅村委会","code":"431127102212"},{"level":"5","name":"清溪村委会","code":"431127102213"},{"level":"5","name":"上洞村委会","code":"431127102214"},{"level":"5","name":"卢溪村委会","code":"431127102215"},{"level":"5","name":"栗树脚村委会","code":"431127102216"},{"level":"5","name":"邓家围村委会","code":"431127102217"},{"level":"5","name":"山溪村委会","code":"431127102218"},{"level":"5","name":"火市村委会","code":"431127102219"},{"level":"5","name":"排下村委会","code":"431127102220"},{"level":"5","name":"岩丘村委会","code":"431127102221"},{"level":"5","name":"大汉口村委会","code":"431127102222"},{"level":"5","name":"井湾村委会","code":"431127102223"},{"level":"5","name":"溪林村委会","code":"431127102224"},{"level":"5","name":"杨梅村委会","code":"431127102225"},{"level":"5","name":"苗昌岭村委会","code":"431127102226"},{"level":"5","name":"社下村委会","code":"431127102227"},{"level":"5","name":"昌头坪村委会","code":"431127102228"},{"level":"5","name":"湖海村委会","code":"431127102229"},{"level":"5","name":"六甲村委会","code":"431127102230"},{"level":"5","name":"七甲村委会","code":"431127102231"},{"level":"5","name":"八甲村委会","code":"431127102232"},{"level":"5","name":"牛栏塘村委会","code":"431127102233"},{"level":"5","name":"马山下村委会","code":"431127102234"},{"level":"5","name":"小江洞村委会","code":"431127102235"},{"level":"5","name":"牛路脚村委会","code":"431127102236"},{"level":"5","name":"雷家岭村委会","code":"431127102237"},{"level":"5","name":"百叠岭村委会","code":"431127102238"},{"level":"5","name":"罗家村委会","code":"431127102239"},{"level":"5","name":"归龙村委会","code":"431127102240"},{"level":"5","name":"礼河村委会","code":"431127102241"},{"level":"5","name":"禾家田村委会","code":"431127102242"},{"level":"5","name":"云峰村委会","code":"431127102243"},{"level":"5","name":"羊尾村委会","code":"431127102244"},{"level":"5","name":"沙坪村委会","code":"431127102245"},{"level":"5","name":"小累村委会","code":"431127102246"},{"level":"5","name":"杨家洞村委会","code":"431127102247"},{"level":"5","name":"刘家寨村委会","code":"431127102248"},{"level":"5","name":"漕溪村委会","code":"431127102249"},{"level":"5","name":"西海村委会","code":"431127102250"}]}