{"villages":[{"level":"5","name":"三口村村委会","code":"431224216200"},{"level":"5","name":"粟溪村村委会","code":"431224216201"},{"level":"5","name":"何家村村委会","code":"431224216202"},{"level":"5","name":"羊角村村委会","code":"431224216203"},{"level":"5","name":"古台村村委会","code":"431224216204"},{"level":"5","name":"将溪村村委会","code":"431224216205"},{"level":"5","name":"梓木村村委会","code":"431224216206"},{"level":"5","name":"蛟溪村村委会","code":"431224216207"},{"level":"5","name":"双江村村委会","code":"431224216208"},{"level":"5","name":"木壕村村委会","code":"431224216209"},{"level":"5","name":"陶金村村委会","code":"431224216210"},{"level":"5","name":"朱溪村村委会","code":"431224216211"},{"level":"5","name":"梨园村村委会","code":"431224216212"},{"level":"5","name":"栗坪村村委会","code":"431224216213"},{"level":"5","name":"十九溪村村委会","code":"431224216214"},{"level":"5","name":"十字村村委会","code":"431224216215"},{"level":"5","name":"大兴村村委会","code":"431224216216"},{"level":"5","name":"石牛村村委会","code":"431224216217"},{"level":"5","name":"梅通村村委会","code":"431224216218"},{"level":"5","name":"竹园村村委会","code":"431224216219"}]}