{"villages":[{"level":"5","name":"百朋居委会","code":"450221102001"},{"level":"5","name":"百朋村委会","code":"450221102201"},{"level":"5","name":"五九村委会","code":"450221102202"},{"level":"5","name":"里团村委会","code":"450221102203"},{"level":"5","name":"怀洪村委会","code":"450221102204"},{"level":"5","name":"官塘村委会","code":"450221102205"},{"level":"5","name":"琴屯村委会","code":"450221102206"},{"level":"5","name":"恭桐村委会","code":"450221102207"},{"level":"5","name":"根林村委会","code":"450221102208"},{"level":"5","name":"小山村委会","code":"450221102209"},{"level":"5","name":"分龙村委会","code":"450221102210"},{"level":"5","name":"鱼龙村委会","code":"450221102211"},{"level":"5","name":"尧治村委会","code":"450221102212"},{"level":"5","name":"龙泉村委会","code":"450221102213"},{"level":"5","name":"镇西村委会","code":"450221102214"},{"level":"5","name":"白诺村委会","code":"450221102215"}]}