{"villages":[{"level":"5","name":"新兴社区居委会","code":"451402106001"},{"level":"5","name":"繁荣社区居委会","code":"451402106002"},{"level":"5","name":"雷州社区居委会","code":"451402106003"},{"level":"5","name":"岜白村委会","code":"451402106201"},{"level":"5","name":"农里村委会","code":"451402106202"},{"level":"5","name":"灶瓦村委会","code":"451402106203"},{"level":"5","name":"伏廖村委会","code":"451402106204"},{"level":"5","name":"那模村委会","code":"451402106205"},{"level":"5","name":"屯村村委会","code":"451402106206"},{"level":"5","name":"崇王村委会","code":"451402106207"},{"level":"5","name":"更兰村委会","code":"451402106208"},{"level":"5","name":"连塘村委会","code":"451402106209"},{"level":"5","name":"渠邦村委会","code":"451402106210"},{"level":"5","name":"驮目村委会","code":"451402106211"},{"level":"5","name":"江涨村委会","code":"451402106212"},{"level":"5","name":"渠立村委会","code":"451402106213"},{"level":"5","name":"逐盎村委会","code":"451402106214"},{"level":"5","name":"岑豆村委会","code":"451402106215"},{"level":"5","name":"驮柏村委会","code":"451402106216"},{"level":"5","name":"谭垌村委会","code":"451402106217"}]}