{"villages":[{"level":"5","name":"玉柱社区居委会","code":"500242100001"},{"level":"5","name":"城东社区居委会","code":"500242100002"},{"level":"5","name":"城北社区居委会","code":"500242100003"},{"level":"5","name":"城南社区居委会","code":"500242100004"},{"level":"5","name":"桃花源社区居委会","code":"500242100005"},{"level":"5","name":"龙池村委会","code":"500242100200"},{"level":"5","name":"双福村委会","code":"500242100201"},{"level":"5","name":"花园村委会","code":"500242100202"},{"level":"5","name":"东流口村委会","code":"500242100203"},{"level":"5","name":"天山堡村委会","code":"500242100204"},{"level":"5","name":"凉风村委会","code":"500242100205"},{"level":"5","name":"钟坨村委会","code":"500242100206"},{"level":"5","name":"梁家堡村委会","code":"500242100207"},{"level":"5","name":"洞底村委会","code":"500242100208"},{"level":"5","name":"青山村委会","code":"500242100209"}]}