{"villages":[{"level":"5","name":"场镇社区居民委员会","code":"510703104001"},{"level":"5","name":"?龙社区居民委员会","code":"510703104002"},{"level":"5","name":"小桥村民委员会","code":"510703104201"},{"level":"5","name":"黄木村民委员会","code":"510703104202"},{"level":"5","name":"尖峰村民委员会","code":"510703104203"},{"level":"5","name":"九龙村民委员会","code":"510703104204"},{"level":"5","name":"九岭村民委员会","code":"510703104205"},{"level":"5","name":"青霞村民委员会","code":"510703104206"},{"level":"5","name":"香社村民委员会","code":"510703104207"},{"level":"5","name":"中脊村民委员会","code":"510703104208"}]}