{"villages":[{"level":"5","name":"场镇社区居民委员会","code":"510703106001"},{"level":"5","name":"兴顺村民委员会","code":"510703106201"},{"level":"5","name":"广福村民委员会","code":"510703106202"},{"level":"5","name":"凤凰村民委员会","code":"510703106203"},{"level":"5","name":"凉水村民委员会","code":"510703106204"},{"level":"5","name":"中心桥村民委员会","code":"510703106205"},{"level":"5","name":"五龙村民委员会","code":"510703106206"},{"level":"5","name":"孔雀村民委员会","code":"510703106207"},{"level":"5","name":"高桥村民委员会","code":"510703106208"},{"level":"5","name":"幸福村民委员会","code":"510703106209"},{"level":"5","name":"涌泉村民委员会","code":"510703106210"},{"level":"5","name":"长林村民委员会","code":"510703106211"}]}