{"villages":[{"level":"5","name":"下庄村委会","code":"532923104201"},{"level":"5","name":"刘营村委会","code":"532923104202"},{"level":"5","name":"张泗村委会","code":"532923104203"},{"level":"5","name":"江场村委会","code":"532923104204"},{"level":"5","name":"鱼进村委会","code":"532923104205"},{"level":"5","name":"赵营村委会","code":"532923104206"},{"level":"5","name":"老张村委会","code":"532923104207"},{"level":"5","name":"沐滂村委会","code":"532923104208"},{"level":"5","name":"大仓村委会","code":"532923104209"},{"level":"5","name":"金旦村委会","code":"532923104210"},{"level":"5","name":"水盆村委会","code":"532923104211"},{"level":"5","name":"纸房村委会","code":"532923104212"}]}