{"villages":[{"level":"5","name":"强旺村","code":"542323208201"},{"level":"5","name":"加热村","code":"542323208202"},{"level":"5","name":"达龙村","code":"542323208203"},{"level":"5","name":"卓热村","code":"542323208204"},{"level":"5","name":"宗卓村","code":"542323208205"},{"level":"5","name":"萨拉村","code":"542323208206"},{"level":"5","name":"西堆村","code":"542323208207"},{"level":"5","name":"最康村","code":"542323208208"},{"level":"5","name":"卓庆村","code":"542323208209"},{"level":"5","name":"龙马村","code":"542323208210"}]}