{"villages":[{"level":"5","name":"小石村委会","code":"610426103200"},{"level":"5","name":"南咀村委会","code":"610426103201"},{"level":"5","name":"王家庄村委会","code":"610426103202"},{"level":"5","name":"河道村委会","code":"610426103203"},{"level":"5","name":"上邱村委会","code":"610426103204"},{"level":"5","name":"侯家村委会","code":"610426103205"},{"level":"5","name":"王家咀村委会","code":"610426103206"},{"level":"5","name":"仪井村委会","code":"610426103207"},{"level":"5","name":"樊家村委会","code":"610426103208"},{"level":"5","name":"宋家村委会","code":"610426103209"},{"level":"5","name":"陆家塬村委会","code":"610426103210"},{"level":"5","name":"康家村委会","code":"610426103211"},{"level":"5","name":"陈马村委会","code":"610426103212"},{"level":"5","name":"孙蒙村委会","code":"610426103213"},{"level":"5","name":"樊宋山村委会","code":"610426103214"},{"level":"5","name":"南曹德村委会","code":"610426103215"},{"level":"5","name":"丰杜村委会","code":"610426103216"},{"level":"5","name":"北曹德村委会","code":"610426103217"}]}