{"villages":[{"level":"5","name":"褒河居委会","code":"610702102001"},{"level":"5","name":"河东店村委会","code":"610702102200"},{"level":"5","name":"周寨村委会","code":"610702102201"},{"level":"5","name":"张寨村委会","code":"610702102202"},{"level":"5","name":"邹马村委会","code":"610702102203"},{"level":"5","name":"磨里村委会","code":"610702102204"},{"level":"5","name":"瞿鲁营村委会","code":"610702102205"},{"level":"5","name":"花果村委会","code":"610702102206"},{"level":"5","name":"黎明村委会","code":"610702102207"},{"level":"5","name":"光明村委会","code":"610702102208"},{"level":"5","name":"平安村委会","code":"610702102209"},{"level":"5","name":"老丈沟村委会","code":"610702102210"},{"level":"5","name":"麻坪寺村委会","code":"610702102211"},{"level":"5","name":"沙河沟村委会","code":"610702102212"},{"level":"5","name":"马家沟村委会","code":"610702102213"},{"level":"5","name":"贯沟村委会","code":"610702102214"},{"level":"5","name":"蚂蝗沟村委会","code":"610702102215"},{"level":"5","name":"三娘坝村委会","code":"610702102216"}]}