{"villages":[{"level":"5","name":"祁家桥村委会","code":"620982102200"},{"level":"5","name":"高台堡村委会","code":"620982102201"},{"level":"5","name":"魏家桥村委会","code":"620982102202"},{"level":"5","name":"肃州庙村委会","code":"620982102203"},{"level":"5","name":"板桥村委会","code":"620982102205"},{"level":"5","name":"武威庙村委会","code":"620982102208"},{"level":"5","name":"河州堡村委会","code":"620982102209"},{"level":"5","name":"孟家桥村委会","code":"620982102210"},{"level":"5","name":"杨家堡村委会","code":"620982102212"},{"level":"5","name":"姚家沟村委会","code":"620982102214"}]}