{"villages":[{"level":"5","name":"罗汉堂村村委会","code":"632523102200"},{"level":"5","name":"尼那村村委会","code":"632523102201"},{"level":"5","name":"多拉村村委会","code":"632523102202"},{"level":"5","name":"曲卜藏村村委会","code":"632523102203"},{"level":"5","name":"昨那村村委会","code":"632523102204"},{"level":"5","name":"豆后浪村村委会","code":"632523102205"},{"level":"5","name":"叶后浪村村委会","code":"632523102206"},{"level":"5","name":"仍果村村委会","code":"632523102207"},{"level":"5","name":"尼那新村村委会","code":"632523102208"},{"level":"5","name":"曲乃海村村委会","code":"632523102209"}]}