{"villages":[{"level":"5","name":"场部村委会","code":"650106501200"},{"level":"5","name":"三坪一连生产队","code":"650106501201"},{"level":"5","name":"三坪二连生产队","code":"650106501202"},{"level":"5","name":"三坪三连生产队","code":"650106501204"},{"level":"5","name":"三坪四连生产队","code":"650106501205"},{"level":"5","name":"三坪五连生产队","code":"650106501206"},{"level":"5","name":"三坪六连生产队","code":"650106501207"},{"level":"5","name":"三坪七连生产队","code":"650106501208"},{"level":"5","name":"三坪八连生产队","code":"650106501209"},{"level":"5","name":"三坪十连生产队","code":"650106501210"},{"level":"5","name":"三坪十一连生产队","code":"650106501211"}]}